luminoth/__init__.py
luminoth/cli.py
luminoth/eval.py
luminoth/io.py
luminoth/predict.py
luminoth/tasks.py
luminoth/train.py
luminoth/train_test.py
luminoth/vis.py
luminoth/datasets/__init__.py
luminoth/datasets/base_dataset.py
luminoth/datasets/datasets.py
luminoth/datasets/exceptions.py
luminoth/datasets/object_detection_dataset.py
luminoth/datasets/object_detection_dataset_test.py
luminoth/models/__init__.py
luminoth/models/models.py
luminoth/models/base/__init__.py
luminoth/models/base/base_network.py
luminoth/models/base/base_network_test.py
luminoth/models/base/truncated_base_network.py
luminoth/models/base/truncated_base_network_test.py
luminoth/models/base/truncated_vgg.py
luminoth/models/fasterrcnn/__init__.py
luminoth/models/fasterrcnn/base_config.yml
luminoth/models/fasterrcnn/fasterrcnn.py
luminoth/models/fasterrcnn/fasterrcnn_test.py
luminoth/models/fasterrcnn/rcnn.py
luminoth/models/fasterrcnn/rcnn_proposal.py
luminoth/models/fasterrcnn/rcnn_proposal_test.py
luminoth/models/fasterrcnn/rcnn_target.py
luminoth/models/fasterrcnn/rcnn_target_test.py
luminoth/models/fasterrcnn/rcnn_test.py
luminoth/models/fasterrcnn/roi_pool.py
luminoth/models/fasterrcnn/roi_pool_test.py
luminoth/models/fasterrcnn/rpn.py
luminoth/models/fasterrcnn/rpn_proposal.py
luminoth/models/fasterrcnn/rpn_proposal_test.py
luminoth/models/fasterrcnn/rpn_target.py
luminoth/models/fasterrcnn/rpn_target_test.py
luminoth/models/fasterrcnn/rpn_test.py
luminoth/models/ssd/__init__.py
luminoth/models/ssd/base_config.yml
luminoth/models/ssd/feature_extractor.py
luminoth/models/ssd/proposal.py
luminoth/models/ssd/ssd.py
luminoth/models/ssd/target.py
luminoth/models/ssd/utils.py
luminoth/tools/__init__.py
luminoth/tools/checkpoint/__init__.py
luminoth/tools/cloud/__init__.py
luminoth/tools/cloud/cli.py
luminoth/tools/cloud/gcloud.py
luminoth/tools/dataset/__init__.py
luminoth/tools/dataset/cli.py
luminoth/tools/dataset/merge.py
luminoth/tools/dataset/transform.py
luminoth-0.2.3.dist-info/LICENSE
luminoth-0.2.3.dist-info/METADATA
luminoth-0.2.3.dist-info/WHEEL
luminoth-0.2.3.dist-info/entry_points.txt
luminoth-0.2.3.dist-info/top_level.txt
luminoth-0.2.3.dist-info/RECORD
