Metadata-Version: 2.1
Name: luminoth
Version: 0.2.3
Summary: Computer vision toolkit based on TensorFlow
Home-page: https://luminoth.ai
Author: Tryolabs
Author-email: luminoth@tryolabs.com
Maintainer: Tryolabs
Maintainer-email: luminoth@tryolabs.com
License: BSD 3-Clause License
Platform: UNKNOWN
Classifier: Development Status :: 2 - Pre-Alpha
Classifier: Intended Audience :: Developers
Classifier: Intended Audience :: Education
Classifier: Intended Audience :: Science/Research
Classifier: Natural Language :: English
Classifier: License :: OSI Approved :: BSD License
Classifier: Topic :: Scientific/Engineering :: Mathematics
Classifier: Topic :: Software Development :: Libraries :: Python Modules
Classifier: Topic :: Software Development :: Libraries
Classifier: Programming Language :: Python
Classifier: Programming Language :: Python :: 2
Classifier: Programming Language :: Python :: 2.7
Classifier: Programming Language :: Python :: 3
Classifier: Programming Language :: Python :: 3.4
Classifier: Programming Language :: Python :: 3.5
Classifier: Programming Language :: Python :: 3.6
Requires-Python: >=2.7, !=3.0.*, !=3.1.*, !=3.2.*
Requires-Dist: Pillow
Requires-Dist: lxml
Requires-Dist: numpy
Requires-Dist: requests
Requires-Dist: scikit-video
Requires-Dist: Flask (>=0.12)
Requires-Dist: PyYAML (<4,>=3.12)
Requires-Dist: click (<7,>=6.7)
Requires-Dist: dm-sonnet (<=1.23,>=1.12)
Requires-Dist: easydict (<=1.8,>=1.7)
Requires-Dist: six (>=1.11)
Provides-Extra: gcloud
Requires-Dist: google-api-python-client (<2,>=1.6.2); extra == 'gcloud'
Requires-Dist: google-cloud-storage (>=1.2.0); extra == 'gcloud'
Requires-Dist: oauth2client (>=4.1.2); extra == 'gcloud'
Requires-Dist: pyasn1 (>=0.4.2); extra == 'gcloud'
Provides-Extra: tf
Requires-Dist: tensorflow (>=1.5); extra == 'tf'
Provides-Extra: tf-gpu
Requires-Dist: tensorflow-gpu (>=); extra == 'tf-gpu'
